beavers/__init__.py
beavers/assets/favicon.ico
beavers/dag.py
beavers/kafka.py
beavers/pandas_wrapper.py
beavers/perspective_wrapper.py
beavers/pyarrow_kafka.py
beavers/pyarrow_replay.py
beavers/pyarrow_wrapper.py
beavers/replay.py
beavers/table.html
beavers/testing.py
beavers-0.12.1.dist-info/LICENSE
beavers-0.12.1.dist-info/METADATA
beavers-0.12.1.dist-info/WHEEL
beavers-0.12.1.dist-info/RECORD
