Metadata-Version: 2.3
Name: beavers
Version: 0.12.1
Summary: Python stream processing
License: Apache-2.0
Keywords: apache-arrow,streaming,data
Author: Tradewell Tech
Author-email: engineering@tradewelltech.co
Maintainer: 0x26res
Maintainer-email: 0x26res@gmail.com
Requires-Python: >=3.10,<4
Classifier: Development Status :: 5 - Production/Stable
Classifier: License :: OSI Approved :: Apache Software License
Classifier: Natural Language :: English
Classifier: Programming Language :: Python :: 3
Classifier: Programming Language :: Python :: 3.10
Classifier: Programming Language :: Python :: 3.11
Classifier: Programming Language :: Python :: 3.12
Classifier: Programming Language :: Python :: 3.13
Provides-Extra: confluent-kafka
Provides-Extra: perspective-python
Provides-Extra: pyarrow
Requires-Dist: confluent_kafka (>=2.1.1) ; extra == "confluent-kafka"
Requires-Dist: pandas (>1.4.0)
Requires-Dist: perspective-python (>=3.0.0) ; extra == "perspective-python"
Requires-Dist: pyarrow (>=12.0) ; extra == "pyarrow"
Requires-Dist: tornado ; extra == "perspective-python"
Project-URL: Bug Tracker, https://github.com/tradewelltech/beavers/issues
Project-URL: Changelog, https://github.com/tradewelltech/beavers/blob/main/CHANGELOG.md
Project-URL: Documentation, https://beavers.readthedocs.io/en/latest/
Project-URL: Repository, https://github.com/tradewelltech/beavers
